{"files":{"packages/shared/dist/types/polymarket.js.map":{"size":132,"mtime_nanos":1776840942344449202,"mode":420,"is_dir":false},"packages/shared/dist/index.d.ts":{"size":195,"mtime_nanos":1776840942338396685,"mode":420,"is_dir":false},"packages/shared/dist/types/macro.js.map":{"size":126,"mtime_nanos":1776840942340064326,"mode":420,"is_dir":false},"packages/shared/dist/types/news.d.ts":{"size":188,"mtime_nanos":1776840942341477007,"mode":420,"is_dir":false},"packages/shared/dist/types/mm.js.map":{"size":105,"mtime_nanos":1776840942341207212,"mode":420,"is_dir":false},"packages/shared/dist/types/news.js.map":{"size":109,"mtime_nanos":1776840942342089054,"mode":420,"is_dir":false},"packages/shared/dist/types/onchain.d.ts":{"size":1119,"mtime_nanos":1776840942342250514,"mode":420,"is_dir":false},"packages/shared/dist/types/mm.d.ts":{"size":213,"mtime_nanos":1776840942340891709,"mode":420,"is_dir":false},"packages/shared/dist/index.d.ts.map":{"size":222,"mtime_nanos":1776840942338643563,"mode":420,"is_dir":false},"packages/shared/.turbo/turbo-build.log":{"size":90,"mtime_nanos":1776225708690711848,"mode":420,"is_dir":false},"packages/shared/dist/types/polymarket.d.ts":{"size":1452,"mtime_nanos":1776840942343474942,"mode":420,"is_dir":false},"packages/shared/dist/types/signal.js.map":{"size":137,"mtime_nanos":1776840942345168750,"mode":420,"is_dir":false},"packages/shared/dist/types/market.js.map":{"size":113,"mtime_nanos":1776840942340746208,"mode":420,"is_dir":false},"packages/shared/dist/types/market.d.ts":{"size":549,"mtime_nanos":1776840942340136577,"mode":420,"is_dir":false},"packages/shared/dist/types/knowledge.d.ts.map":{"size":2201,"mtime_nanos":1776840942339593572,"mode":420,"is_dir":false},"packages/shared/dist/types/onchain.d.ts.map":{"size":1218,"mtime_nanos":1776840942342600476,"mode":420,"is_dir":false},"packages/shared/dist/types/news.js":{"size":43,"mtime_nanos":1776840942341903427,"mode":420,"is_dir":false},"packages/shared/dist/types/knowledge.js.map":{"size":139,"mtime_nanos":1776840942339779407,"mode":420,"is_dir":false},"packages/shared/dist/types/knowledge.d.ts":{"size":2814,"mtime_nanos":1776840942339458529,"mode":420,"is_dir":false},"packages/shared/dist/types/mm.d.ts.map":{"size":286,"mtime_nanos":1776840942341024461,"mode":420,"is_dir":false},"packages/shared/dist/types/signal.js":{"size":173,"mtime_nanos":1776840942345067624,"mode":420,"is_dir":false},"packages/shared/dist/types/market.js":{"size":45,"mtime_nanos":1776840942340575831,"mode":420,"is_dir":false},"packages/shared/dist/index.js":{"size":44,"mtime_nanos":1776840942338844231,"mode":420,"is_dir":false},"packages/shared/dist/types/market.d.ts.map":{"size":744,"mtime_nanos":1776840942340366829,"mode":420,"is_dir":false},"packages/shared/dist/types/knowledge.js":{"size":509,"mtime_nanos":1776840942339696489,"mode":420,"is_dir":false},"packages/shared/dist/types/signal.d.ts.map":{"size":688,"mtime_nanos":1776840942344713454,"mode":420,"is_dir":false},"packages/shared/dist/index.js.map":{"size":102,"mtime_nanos":1776840942339020983,"mode":420,"is_dir":false},"packages/shared/dist/types/mm.js":{"size":41,"mtime_nanos":1776840942341126420,"mode":420,"is_dir":false},"packages/shared/dist/types/signal.d.ts":{"size":561,"mtime_nanos":1776840942344532578,"mode":420,"is_dir":false},"packages/shared/dist/types/macro.js":{"size":372,"mtime_nanos":1776840942339996659,"mode":420,"is_dir":false},"packages/shared/dist/types/macro.d.ts":{"size":1916,"mtime_nanos":1776840942339857241,"mode":420,"is_dir":false},"packages/shared/dist/types/onchain.js.map":{"size":115,"mtime_nanos":1776840942343281816,"mode":420,"is_dir":false},"packages/shared/dist/types/polymarket.d.ts.map":{"size":1601,"mtime_nanos":1776840942344106782,"mode":420,"is_dir":false},"packages/shared/dist/types/polymarket.js":{"size":127,"mtime_nanos":1776840942344360159,"mode":420,"is_dir":false},"packages/shared/dist/types/macro.d.ts.map":{"size":1073,"mtime_nanos":1776840942339928117,"mode":420,"is_dir":false},"packages/shared/dist/types/onchain.js":{"size":46,"mtime_nanos":1776840942342734685,"mode":420,"is_dir":false},"packages/shared/dist/types/news.d.ts.map":{"size":289,"mtime_nanos":1776840942341716217,"mode":420,"is_dir":false}},"order":["packages/shared/.turbo/turbo-build.log","packages/shared/dist/index.d.ts","packages/shared/dist/index.d.ts.map","packages/shared/dist/index.js","packages/shared/dist/index.js.map","packages/shared/dist/types/knowledge.d.ts","packages/shared/dist/types/knowledge.d.ts.map","packages/shared/dist/types/knowledge.js","packages/shared/dist/types/knowledge.js.map","packages/shared/dist/types/macro.d.ts","packages/shared/dist/types/macro.d.ts.map","packages/shared/dist/types/macro.js","packages/shared/dist/types/macro.js.map","packages/shared/dist/types/market.d.ts","packages/shared/dist/types/market.d.ts.map","packages/shared/dist/types/market.js","packages/shared/dist/types/market.js.map","packages/shared/dist/types/mm.d.ts","packages/shared/dist/types/mm.d.ts.map","packages/shared/dist/types/mm.js","packages/shared/dist/types/mm.js.map","packages/shared/dist/types/news.d.ts","packages/shared/dist/types/news.d.ts.map","packages/shared/dist/types/news.js","packages/shared/dist/types/news.js.map","packages/shared/dist/types/onchain.d.ts","packages/shared/dist/types/onchain.d.ts.map","packages/shared/dist/types/onchain.js","packages/shared/dist/types/onchain.js.map","packages/shared/dist/types/polymarket.d.ts","packages/shared/dist/types/polymarket.d.ts.map","packages/shared/dist/types/polymarket.js","packages/shared/dist/types/polymarket.js.map","packages/shared/dist/types/signal.d.ts","packages/shared/dist/types/signal.d.ts.map","packages/shared/dist/types/signal.js","packages/shared/dist/types/signal.js.map"]}